veadk/__init__.py
veadk/agent.py
veadk/agent_builder.py
veadk/config.py
veadk/consts.py
veadk/runner.py
veadk/types.py
veadk/version.py
veadk/a2a/__init__.py
veadk/a2a/agent_card.py
veadk/a2a/remote_ve_agent.py
veadk/a2a/ve_a2a_server.py
veadk/a2a/ve_agent_executor.py
veadk/a2a/ve_middlewares.py
veadk/a2a/ve_task_store.py
veadk/a2a/hub/__init__.py
veadk/a2a/hub/a2a_hub_client.py
veadk/a2a/hub/a2a_hub_server.py
veadk/a2a/hub/models.py
veadk/a2a/utils/__init__.py
veadk/a2a/utils/agent_to_a2a.py
veadk/agents/loop_agent.py
veadk/agents/parallel_agent.py
veadk/agents/sequential_agent.py
veadk/auth/__init__.py
veadk/auth/base_auth.py
veadk/auth/ve_credential_service.py
veadk/auth/veauth/__init__.py
veadk/auth/veauth/apmplus_veauth.py
veadk/auth/veauth/ark_veauth.py
veadk/auth/veauth/base_veauth.py
veadk/auth/veauth/cozeloop_veauth.py
veadk/auth/veauth/mse_veauth.py
veadk/auth/veauth/opensearch_veauth.py
veadk/auth/veauth/postgresql_veauth.py
veadk/auth/veauth/prompt_pilot_veauth.py
veadk/auth/veauth/speech_veauth.py
veadk/auth/veauth/utils.py
veadk/auth/veauth/vesearch_veauth.py
veadk/auth/veauth/viking_mem0_veauth.py
veadk/cli/__init__.py
veadk/cli/cli.py
veadk/cli/cli_agentkit.py
veadk/cli/cli_clean.py
veadk/cli/cli_create.py
veadk/cli/cli_deploy.py
veadk/cli/cli_eval.py
veadk/cli/cli_init.py
veadk/cli/cli_kb.py
veadk/cli/cli_pipeline.py
veadk/cli/cli_prompt.py
veadk/cli/cli_rl.py
veadk/cli/cli_update.py
veadk/cli/cli_uploadevalset.py
veadk/cli/cli_web.py
veadk/cli/templates/rl/ark/README.md
veadk/cli/templates/rl/ark/arkworkspace.toml
veadk/cli/templates/rl/ark/job.py
veadk/cli/templates/rl/ark/job.yaml
veadk/cli/templates/rl/ark/requirements.txt
veadk/cli/templates/rl/ark/test_faas.py
veadk/cli/templates/rl/ark/data/demo_dataset.jsonl
veadk/cli/templates/rl/ark/plugins/random_reward.py
veadk/cli/templates/rl/ark/plugins/raw_async_veadk_rollout.py
veadk/cli/templates/rl/ark/plugins/test_utils.py
veadk/cli/templates/rl/lightning/README.md
veadk_python-0.5.7.dist-info/licenses/LICENSE
veadk_python-0.5.7.dist-info/METADATA
veadk_python-0.5.7.dist-info/WHEEL
veadk_python-0.5.7.dist-info/entry_points.txt
veadk_python-0.5.7.dist-info/top_level.txt
veadk_python-0.5.7.dist-info/RECORD
