Metadata-Version: 2.4
Name: veadk-python
Version: 0.5.7
Summary: Volcengine agent development kit, integrations with Volcengine cloud services.
Author-email: Yaozheng Fang <fangyozheng@gmail.com>, Guodong Li <cu.eric.lee@gmail.com>, Zhi Han <sliverydayday@gmail.com>, Meng Wang <mengwangwm@gmail.com>
License:                                  Apache License
Requires-Python: >=3.10
License-File: LICENSE
Requires-Dist: pydantic-settings==2.10.1
Requires-Dist: a2a-sdk>=0.3.7
Requires-Dist: deprecated==1.2.18
Requires-Dist: google-adk>=1.19.0
Requires-Dist: litellm>=1.74.3
Requires-Dist: loguru==0.7.3
Requires-Dist: opentelemetry-exporter-otlp==1.37.0
Requires-Dist: opentelemetry-instrumentation-logging>=0.56b0
Requires-Dist: wrapt==1.17.2
Requires-Dist: volcengine-python-sdk>=5.0.1
Requires-Dist: volcengine>=1.0.193
Requires-Dist: agent-pilot-sdk==0.1.2
Requires-Dist: fastmcp>=2.12.3
Requires-Dist: trustedmcp==0.0.5
Requires-Dist: cookiecutter==2.6.0
Requires-Dist: omegaconf==2.3.0
Requires-Dist: llama-index==0.14.0
Requires-Dist: llama-index-embeddings-openai-like==0.2.2
Requires-Dist: llama-index-llms-openai-like==0.5.1
Requires-Dist: llama-index-vector-stores-opensearch==0.6.1
Requires-Dist: psycopg2-binary==2.9.10
Requires-Dist: asyncpg>=0.29.0
Requires-Dist: pymysql==1.1.1
Requires-Dist: aiomysql==0.3.2
Requires-Dist: opensearch-py==2.8.0
Requires-Dist: filetype==1.2.0
Requires-Dist: vikingdb-python-sdk>=0.1.3
Requires-Dist: agentkit-sdk-python>=0.2.0
Requires-Dist: python-frontmatter==1.1.0
Provides-Extra: extensions
Requires-Dist: redis>=5.0; extra == "extensions"
Requires-Dist: tos>=2.8.4; extra == "extensions"
Requires-Dist: llama-index-vector-stores-redis>=0.6.1; extra == "extensions"
Requires-Dist: cozeloop>=0.1.21; extra == "extensions"
Provides-Extra: database
Requires-Dist: redis>=5.0; extra == "database"
Requires-Dist: pymysql>=1.1.1; extra == "database"
Requires-Dist: volcengine>=1.0.193; extra == "database"
Requires-Dist: tos>=2.8.4; extra == "database"
Requires-Dist: mem0ai==0.1.118; extra == "database"
Provides-Extra: speech
Provides-Extra: eval
Requires-Dist: prometheus-client>=0.22.1; extra == "eval"
Requires-Dist: deepeval>=3.2.6; extra == "eval"
Requires-Dist: google-adk[eval]; extra == "eval"
Provides-Extra: cli
Provides-Extra: dev
Requires-Dist: pre-commit>=4.2.0; extra == "dev"
Requires-Dist: pytest>=8.4.1; extra == "dev"
Requires-Dist: pytest-asyncio>=1.0.0; extra == "dev"
Requires-Dist: pytest-xdist>=3.8.0; extra == "dev"
Dynamic: license-file
